correctionlib/JSONEncoder.py
correctionlib/cli.py
correctionlib/highlevel.py
correctionlib/_core.cpython-37m-i386-linux-gnu.so
correctionlib/__init__.py
correctionlib/version.py
correctionlib/schemav1.py
correctionlib/binding.py
correctionlib/schemav2.py
correctionlib/convert.py
correctionlib/util.py
correctionlib/lib/libcorrectionlib.so
correctionlib/cmake/correctionlib-targets.cmake
correctionlib/cmake/correctionlib-targets-release.cmake
correctionlib/cmake/correctionlibConfigVersion.cmake
correctionlib/cmake/correctionlibConfig.cmake
correctionlib/include/correctionlib_version.h
correctionlib/include/correction.h
correctionlib-2.6.4.dist-info/RECORD
correctionlib-2.6.4.dist-info/entry_points.txt
correctionlib-2.6.4.dist-info/WHEEL
correctionlib-2.6.4.dist-info/LICENSE
correctionlib-2.6.4.dist-info/top_level.txt
correctionlib-2.6.4.dist-info/METADATA
