Metadata-Version: 2.1
Name: correctionlib
Version: 2.6.4
Summary: A generic correction library
Home-page: https://github.com/cms-nanoAOD/correctionlib
Author: Nick Smith
Author-email: nick.smith@cern.ch
Maintainer: Nick Smith
Maintainer-email: nick.smith@cern.ch
License: BSD 3-Clause License
Platform: Any
Classifier: Topic :: Scientific/Engineering
Classifier: Intended Audience :: Science/Research
Classifier: Intended Audience :: Developers
Classifier: Operating System :: OS Independent
Classifier: License :: OSI Approved :: BSD License
Classifier: Programming Language :: Python
Classifier: Programming Language :: Python :: 3
Classifier: Development Status :: 5 - Production/Stable
Requires-Python: >=3.7
License-File: LICENSE
Requires-Dist: numpy>=1.13.3
Requires-Dist: typing-extensions; python_version < "3.8"
Requires-Dist: dataclasses; python_version < "3.7"
Requires-Dist: pydantic>=2
Requires-Dist: rich
Requires-Dist: packaging
Provides-Extra: test
Requires-Dist: pytest>=4.6; extra == "test"
Requires-Dist: scipy; extra == "test"
Requires-Dist: awkward>=2.2.2; python_version > "3.7" and extra == "test"
Requires-Dist: awkward<2; python_version <= "3.7" and extra == "test"
Requires-Dist: dask-awkward>=2024.1.1; python_version > "3.7" and extra == "test"
Provides-Extra: dev
Requires-Dist: pytest>=4.6; extra == "dev"
Requires-Dist: pre-commit; extra == "dev"
Requires-Dist: mypy; extra == "dev"
Requires-Dist: uhi; extra == "dev"
Requires-Dist: awkward>=2; extra == "dev"
Requires-Dist: dask-awkward; python_version > "3.7" and extra == "dev"
Provides-Extra: docs
Requires-Dist: recommonmark>=0.5.0; extra == "docs"
Requires-Dist: Sphinx>=3.0.0; extra == "docs"
Requires-Dist: sphinx_copybutton; extra == "docs"
Requires-Dist: sphinx_rtd_theme>=0.5.0; extra == "docs"
Requires-Dist: sphinx-jsonschema; extra == "docs"
Requires-Dist: myst-parser; extra == "docs"
Requires-Dist: nbsphinx; extra == "docs"
Provides-Extra: convert
Requires-Dist: pandas; extra == "convert"
Requires-Dist: uproot>=4.0.4; extra == "convert"
Requires-Dist: requests; extra == "convert"
Requires-Dist: scipy; extra == "convert"
